{
  "gitSyncId": "6703b251c982f54ff180d40c_b18958a4-a88a-4336-a27a-dbb6a551dd53",
  "id": "Projects_GetComponents",
  "pluginId": "postgres-plugin",
  "pluginType": "DB",
  "unpublishedAction": {
    "actionConfiguration": {
      "body": "SELECT * FROM components",
      "encodeParamsToggle": true,
      "paginationType": "NONE",
      "pluginSpecifiedTemplates": [
        {
          "value": true
        }
      ],
      "timeoutInMillisecond": 10000
    },
    "confirmBeforeExecute": false,
    "datasource": {
      "id": "Koyeb Postgres DB",
      "isAutoGenerated": false,
      "name": "Koyeb Postgres DB",
      "pluginId": "postgres-plugin"
    },
    "dynamicBindingPathList": [],
    "executeOnLoad": true,
    "name": "GetComponents",
    "pageId": "Projects",
    "userSetOnLoad": false
  }
}